{
  "search_id": "search_1f7e1f71cc624e21a3196d672c3042af",
  "status": "ok",
  "results": [
    {
      "url": "https://www.darpa.mil/news/2025/roqs-launches-first-phase",
      "title": "From fragile to field-ready: RoQS program launches first phase | DARPA",
      "publish_date": null,
      "excerpts": [
        "An official website of the United States Government\n\nHere\u2019s how you know\n\nHere\u2019s how you know\n\n**Official websites use .mil**  \nA **.mil** website belongs to an official U.S.\nDepartment of War organization.\n\n**Secure .mil websites use HTTPS**  \nA **lock** ( ) or **https://** means you\u2019ve safely connected to the .mil website. Share sensitive information only on official, secure websites.\n\n* Work with Us\n* R&D Opportunities\n* Programs\n* Offices\n* News\n* Events\n* Careers\n* About\n\n## Breadcrumb\n\n1. Home\n2. News\n3. From Fragile To Field-ready: RoQS Program Launches First Phase\n\n# From fragile to field-ready: RoQS program launches first phase\n\n#### Robust Quantum Sensors program invites government collaboration to bring quantum precision to tactical platforms\n\n##### Aug. 27, 2025\nThe Defense Advanced Research Projects Agency (DARPA) has officially launched Phase 1 of its Robust Quantum Sensors (RoQS) program, a groundbreaking effort to make quantum sensing viable beyond the lab \u2013 on the ground, at sea, in the air, and even in space.\n\nQuantum sensors offer unmatched precision in detecting magnetic and electric fields, acceleration, rotation, and gravity, but their extraordinary sensitivity has made them notoriously fragile in real-world environments. Even minor vibrations or electromagnetic interference can degrade performance, limiting their operational use. RoQS is taking a fundamentally new approach to this challenge: not by applying temporary fixes like shielding or isolation, but by rethinking sensor design from the ground up.\n\nRoQS aims to create inherently robust sensors that reject interference, withstand motion, and deliver reliable, state-of-the-art performance across domains.\nThe goal is to break through long-standing barriers to field deployment, accelerate the transition from lab to mission, and unlock new capabilities in navigation, threat detection, and situational awareness.\n\nThe first phase of the program is in progress, with two technical areas kicking off in parallel:\n\n* **Sensor Development:** Performer teams will build compact, \u201cwalk-on/walk-off\u201d quantum sensors and test them on a government-provided helicopter. The helicopter environment was chosen for its inherent challenges \u2013 strong electromagnetic fields, vibrations, and gradients \u2013 so that sensors that pass this test can be trusted to work on a wide range of other Department of Defense (DOD) platforms.\n* **Platform Integration Studies:** Performers will work with the defense industrial base to identify specific Programs of Record (PoRs) and platform types where quantum sensors could deliver strategic value. These could range from ground vehicles and submarines to satellites and UAVs."
      ]
    },
    {
      "url": "https://q-ctrl.com/blog/darpa-selects-q-ctrl-to-develop-next-generation-quantum-sensors-for-navigation-on-advanced-defense-platforms",
      "title": "DARPA Selects Q-CTRL to Develop Next-Generation Quantum ...",
      "publish_date": "2025-08-27",
      "excerpts": [
        "Navigational technology that is resilient to denial, jamming, spoofing, and other denials in the environment has become increasingly critical to defense applications from battlefield operations to intelligence and surveillance. With conflict zones expanding, the risks to crewed and uncrewed defense missions are growing daily. Quantum sensing offers a complementary solution to GPS that is resilient against external interference while filling coverage gaps.\n\nQ-CTRL will develop next-generation quantum sensors for navigation based on their success in field trials of airborne, maritime, and ground-based quantum navigation augmented by their proprietary AI-powered software ruggedization. This technology enables sensors to operate reliably on moving defense platforms subject to challenging real-world conditions, without the need for traditional shielding or isolation.\nQ-CTRL will be joined by Lockheed Martin as a subcontractor on one aspect of the RoQS program, leveraging its expertise in GPS and quantum technology.\n\n[RoQS](https://www.darpa.mil/news/2025/roqs-launches-first-phase) was established by DARPA to accelerate the development, testing, and validation of quantum sensors for real-world defense applications, which include maintaining stability against environmental interference, mechanical vibrations, and heavy g-forces.\n\n> DARPA has an incredible track record of delivering innovations that change the face of society, from the internet and mobile phones to night vision and stealth. We\u2019re honored that our recent demonstrations and exciting new ideas earned Q-CTRL\u2019s selection to deliver a new generation of software-ruggedized quantum sensors for the most challenging defense missions. We\u2019re here to win and are excited to work with the team at DARPA for the benefit of the warfighter. _Michael J Biercuk, CEO and Founder of Q-CTRL._\n> We look forward to supporting Q-CTRL and DARPA in the development of robust quantum-enhanced navigational technology. This award signifies the priority defense agencies are placing on the potential for quantum navigation solutions to deliver transformational national security capabilities that complement GPS. _Thomas Loftus, Senior Fellow at Lockheed Martin._\n\nSome sectors and organizations are fast-maturing quantum navigation for use on land, sea, in space, and in the air. The aerospace industry is actively exploring the potential for magnetic navigation technologies, with companies like aircraft manufacturer Airbus pursuing their development.\n\nAdditionally, Q-CTRL\u2019s programs target the complementary missions of geophysical mapping of gravity and magnetic fields, as well as positioning based on matching detected signals to the pre-generated maps."
      ]
    },
    {
      "url": "https://www.darpa.mil/news/2025/quantum-sensors-defense-platforms",
      "title": "Taking quantum sensors out of the lab and into defense platforms | DARPA",
      "publish_date": null,
      "excerpts": [
        "An official website of the United States Government\n\nHere\u2019s how you know\n\nHere\u2019s how you know\n\n**Official websites use .mil**  \nA **.mil** website belongs to an official U.S.\nDepartment of War organization.\n\n**Secure .mil websites use HTTPS**  \nA **lock** ( ) or **https://** means you\u2019ve safely connected to the .mil website. Share sensitive information only on official, secure websites.\n\n* Work with Us\n* R&D Opportunities\n* Programs\n* Offices\n* News\n* Events\n* Careers\n* About\n\n## Breadcrumb\n\n1. Home\n2. News\n3. Taking Quantum Sensors Out of The Lab and Into Defense Platforms\n\n# Taking quantum sensors out of the lab and into defense platforms\n\n#### DARPA\u2019s Robust Quantum Sensors (RoQS) program seeks to advance quantum sensing technology for use in real-world conditions\n\n##### Feb. 7, 2025\n\nQuantum sensors, which have demonstrated unmatched precision in measuring magnetic fields, gravity, and motion, hold immense promise for advancing defense capabilities.\nHowever, these sensors face significant challenges when deployed in real-world settings \u2013 especially when placed on moving platforms. Vibrations, electromagnetic interference, and other environmental disturbances degrade their performance, limiting their operational utility. Current solutions, such as isolating the sensors or using bulky shielding, are impractical for widespread deployment.\n\nTo address these barriers, DARPA is launching the Robust Quantum Sensors (RoQS) program . RoQS will seek to develop quantum sensors that are inherently resistant to environmental disruptions, ensuring they can operate reliably outside of a laboratory without sacrificing their sensitivity. The ultimate goal of the program is to integrate these sensors into Department of Defense platforms.\n\nRoQS emphasizes early collaboration between sensor developers and platform makers within the defense industrial base to streamline the transition from research to operational deployment.\nBy fostering these partnerships early on, DARPA aims to ensure that the developed technologies meet real-world requirements and can be seamlessly integrated into existing systems \u2013 significantly reducing the time and resources needed to harden and deploy quantum sensors.\n\n\u201cQuantum sensors have the potential to redefine how we gather critical information in defense scenarios,\u201d said Dr. Jonathan Hoffman, Program Manager in DARPA\u2019s Microsystems Technology Office. \u201cHowever, their fragility has been a major barrier to deployment. With RoQS, we\u2019re taking a bold step toward creating sensors that are not only extremely precise but also resilient in the face of real-world challenges.\u201d\n\nThe RoQS program is designed to tackle the problem of sensor fragility at its core. Instead of relying on bulky shielding or isolation techniques that are impractical for widespread use, RoQS will explore new approaches to sensor design and architecture. Potential approaches include:"
      ]
    },
    {
      "url": "https://www.lockheedmartin.com/en-us/news/features/2025/lockheed-martin-Q-CTRL-revolutionizing-navigation-with-quantum-technology.html",
      "title": "Lockheed Martin and Q-CTRL: Revolutionizing Navigation with Quantum Technology | Lockheed Martin",
      "publish_date": "2025-08-27",
      "excerpts": [
        "lockheedmartin.com/en-us/careers/life-at-lm.html)\n\nMy Account\n\n[Early Careers](https://sjobs.brassring.com/TGnewUI/Search/Home/Home?partnerid=25037&siteid=5014&pk_vid=b6c27996c05b2c151732641010904953) [Experienced Professionals](https://sjobs.brassring.com/TGnewUI/Search/Home/Home?partnerid=25037&siteid=5010&pk_vid=b6c27996c05b2c151732641004904953)\n\nBack to the News Hub\n\nLockheed Martin and Q-CTRL: Revolutionizing Navigation with Quantum Technology\n\nAugust 27, 2025\n\n[](https://www.addtoany.com/share)\n\nWith conflict zones expanding, robust backup navigational technology that is resilient to denial, jamming, and spoofing has become increasingly critical to defense applications from battlefield operations to intelligence and surveillance. To address this, Lockheed Martin will be joining [Q-CTRL](https://q-ctrl.\ncom/our-work/positioning-navigation-and-timing) to develop next-generation quantum sensors for navigation on advanced defense platforms for the [DARPA Robust Quantum Sensors (RoQS)](https://www.darpa.mil/research/programs/roqs-robust-quantum-sensors) program leveraging their expertise in both quantum and GPS technology.\n\nThis collaboration comes shortly after Lockheed Martin\u2019s awarded contract by the U.S. Department of Defense's Innovation Unit (DIU) to [prototype quantum-enabled Inertial Navigation System (INS)](https://www.lockheedmartin.com/en-us/news/features/2025/unlocking-the-power-of-quantum-navigation-lockheed-martin-and-partners-awarded-contract.html) . Lockheed Martin partnered with Q-CTRL to develop a system, known as QuINS, which uses quantum sensing technology to provide highly accurate navigation and positioning capabilities.\n\n[Learn More](https://www.darpa.mil/news/2025/roqs-launches-first-phase)\n\nHelpful Links   \\_\\_\\_\n\nWhat We Do Our Capabilities Our Products"
      ]
    },
    {
      "url": "https://executivegov.com/articles/darpa-quantum-sensing-program-phase-1-launch",
      "title": "DARPA's RoQS Program Phase 1 Begins - ExecutiveGov",
      "publish_date": "2025-08-28",
      "excerpts": [
        "app_id=794927004237856&link=https%3A%2F%2Fwww.executivegov.com%2Farticles%2Fdarpa-quantum-sensing-program-phase-1-launch&redirect_uri=https%3A%2F%2Fwww.executivegov.com%2F \"Messenger\")\n* [Twitter](https://twitter.com/intent/tweet?url=https%3A%2F%2Fwww.executivegov.com%2Farticles%2Fdarpa-quantum-sensing-program-phase-1-launch&text=DARPA+Launches+RoQS+Program+Phase+1+to+Develop+Quantum+Sensing+Tech+for+Defense+Use&via=executivegov \"Twitter\")\n* [Whatsapp](https://api.whatsapp.com/send?phone=&text=https%3A%2F%2Fwww.executivegov.com%2Farticles%2Fdarpa-quantum-sensing-program-phase-1-launch \"Whatsapp\")\n* Email\n\nThe Defense Advanced Research Projects Agency has commenced phase one of the Robust Quantum Sensors, or RoQS, program to advance the development of quantum sensing technologies for defense applications.\n\nThe agency said Wednesday that the program has [two technical areas](https://www.darpa.mil/news/2025/roqs-launches-first-phase) running simultaneously.\nThe first technical area involves building and testing compact walk-on/walk-off quantum sensors for government-provided helicopters. DARPA explained that helicopters are associated with strong electromagnetic fields, vibrations and gradients, which are elements that could affect the performance of quantum sensors.\n\nFor the second technical area, participants are tasked to collaborate with the defense industrial base to determine where quantum sensors could generate value. The effort would guide the development of integration and technical requirements for the next phase of the RoQS program.\n\n## DARPA\u2019s Quantum Sensing Challenge\n\nDARPA [launched the RoQS program in February](https://www.executivegov.com/articles/darpa-quantum-sensor-stabilization-abstracts) to accelerate the transition of robust quantum sensors from laboratory to mission, allowing warfighters across all domains to benefit from precise detection of acceleration, rotation, gravity, and magnetic and electric fields."
      ]
    },
    {
      "url": "https://breakingdefense.com/2025/02/roqs-for-a-hard-place-darpa-seeks-radically-more-robust-quantum-sensors-for-inhospitable-fieldwork/",
      "title": "RoQS for a hard place: DARPA seeks radically more 'robust' quantum sensors for 'inhospitable' fieldwork - Breaking Defense",
      "publish_date": "2025-09-17",
      "excerpts": [
        "com/2024/01/quantum-pentagon-must-jumpstart-3-key-applications-urges-afa/) or [hunt submarines without using sonar](https://breakingdefense.com/2024/01/transparent-sea-aukus-looks-to-ai-quantum-in-hunt-for-chinese-submarines/) , to put it on helicopters and jets and satellites, with all the vibration and radiation that entails. In those harsh environments, the same exquisite sensitivity that makes quantum tech such a good sensor also makes it extraordinarily vulnerable to interference, drowning the desired signal in irrelevant noise.\n\nPast efforts to ruggedize quantum sensors have focused on taking today\u2019s finicky lab tech and shielding it from interference: One might wrap a sensor in metal to shield it from electromagnetic radiation, for instance, or install it on a vibration-cancelling boom instead of in the body of an aircraft.\nBut in a new interview with Breaking Defense, Jonathan Hoffman, a program manager at the fringe-science-loving Defense Advanced Research Projects Agency (DARPA), argued that those kinds of Rube Goldberg fixes don\u2019t address the underlying problem. Hoffman\u2019s team is in the midst of a project, dubbed Robust Quantum Sensors or RoQs, that he hopes will discover a fundamentally new approach.\n\n\u201cWe\u2019re looking for ideas that don\u2019t require what I call these \u2018band-aid\u2019 solutions,\u201d Hoffman said. \u201cOur hope is this is a philosophical, foundational change in how we build we quantum sensors. \u2026 Rather than saying \u2018I\u2019m going to shield away the problem,\u2019 how do I, at the very beginning of my sensor design, think about all those interferences and figure out a way around [them]?\u201d\n\nThat\u2019s an extremely difficult problem, and the potential solutions can get esoteric."
      ]
    },
    {
      "url": "http://quantumwire.com/article/17563742284402.html",
      "title": "Robust Quantum Sensors Program Invites Government ...",
      "publish_date": "2025-08-28",
      "excerpts": [
        "August 27, 2025 -- The Defense Advanced Research Projects Agency (DARPA) has officially launched Phase 1 of its Robust Quantum Sensors (RoQS) program, a groundbreaking effort to make quantum sensing viable beyond the lab \u2013 on the ground, at sea, in the air, and even in space."
      ]
    },
    {
      "url": "https://thedefensecircuit.com/2025/09/01/q-ctrl-and-lockheed-martin-join-forces/",
      "title": "Q-CTRL and Lockheed Martin Join Forces Under DARPA\u2019s Quantum Sensing Initiative \u2013 The Defense Circuit",
      "publish_date": "2025-09-01",
      "excerpts": [
        "DARPA\u2019s RoQS program was created to overcome this barrier\u2014accelerating the transition of quantum navigation from the physics lab to the battlefield.\n\nQ-CTRL has emerged as a leader in this transition. The company\u2019s Ironstone Opal quantum navigation system has already demonstrated 111-fold greater accuracy than a high-end inertial navigation system (INS) during flight trials when GPS was unavailable. In maritime trials aboard the Royal Australian Navy\u2019s _MV Sycamore_ , the technology operated continuously for 144 hours, navigating by detecting variations in Earth\u2019s gravity field. What sets Q-CTRL apart is its AI-powered \u201csoftware ruggedization\u201d\u2014a layer of machine learning that stabilizes quantum sensors against the noise and interference of moving platforms. This eliminates the need for bulky shielding or isolation hardware, making the systems more deployable for military use.\n\nCEO Michael J. Biercuk said the DARPA awards validate Q-CTRL\u2019s mission:\n> \u201cDARPA has an incredible track record of delivering innovations that change the face of society, from the internet and mobile phones to night vision and stealth. We\u2019re honored that our demonstrations and new ideas earned selection to deliver a new generation of software-ruggedized quantum sensors for the most challenging defense missions.\u201d\n> \n> \n\nQ-CTRL will collaborate with Lockheed Martin, which brings decades of experience in GPS and navigation technology. The program builds on their prior work with the U.S. Department of Defense\u2019s Defense Innovation Unit (DIU) to prototype a quantum-enabled inertial navigation system, known as QuINS. U.S. government agencies are also taking notice. NASA and the U.S. Geological Survey (USGS) are exploring uses of mobile quantum sensors for subsurface mapping, mineral prospecting, and GPS-denied navigation\u2014applications with both defense and commercial impact."
      ]
    },
    {
      "url": "https://www.darpa.mil/research/programs/roqs-robust-quantum-sensors",
      "title": "RoQS: Robust Quantum Sensors | DARPA",
      "publish_date": null,
      "excerpts": [
        "An official website of the United States Government\n\nHere\u2019s how you know\n\nHere\u2019s how you know\n\n**Official websites use .mil**  \nA **.mil** website belongs to an official U.S.\nDepartment of War organization.\n\n**Secure .mil websites use HTTPS**  \nA **lock** ( ) or **https://** means you\u2019ve safely connected to the .mil website. Share sensitive information only on official, secure websites.\n\n* Work with Us\n* R&D Opportunities\n* Programs\n* Offices\n* News\n* Events\n* Careers\n* About\n\n## Breadcrumb\n\n1. Home\n2. Research\n3. Programs\n4. RoQS: Robust Quantum Sensors\n\n# RoQS: Robust Quantum Sensors\n\n#### How to develop sensors that resist performance degradation\n\nThe Robust Quantum Sensors (RoQS) program will advance quantum sensing technology for use on Department of Defense platforms.\n\nWhile quantum sensors have shown exceptional capabilities in controlled settings, their performance often declines in dynamic environments due to factors such as vibrations and electromagnetic interference.\nRoQS seeks to address these challenges by developing sensors that resist performance degradation in real-world conditions.\n\n##### Resources\n\n* Proposers Day presentation\n* FAQs\n\n##### Office\n\nMicrosystems Technology Office\n\n##### Program manager\n\n###### Jonathan Hoffman\n\nRead bio\n\n##### Related content\n\n* From fragile to field-ready: RoQS program launches first phase\n* Taking quantum sensors out of the lab and into defense platforms\n\n##### Opportunity\n\nDARPA-PS-25-11  \n[Solicitation](https://sam.gov/opp/c0368342762645a794d66341be88dfba/view)\n\n## Contact\n\n### Work with DARPA\n\nBe part of a cutting-edge research and development agency that\u2019s pushing the boundaries of what\u2019s possible, in an energetic environment with excellent benefits.\n\nFind your future with DARPA Careers >\n\nOur program managers are visionary leaders whose experience spans industry, government, and academia. They conceive, plan, and oversee the high-risk R&D efforts for which we are best known.\nSee all people at DARPA >\n\nResearch Opportunities\n\n### Redefining Possible\n\nDARPA has pushed, and will continue to push, the boundaries of technological possibility.\n\nSee the dreams we turned to reality\n\n## USA Government Links\n\n* [DoD Hotline](https://www.dodig.mil/Components/Administrative-Investigations/DoD-Hotline/)\n* Freedom of Information Act\n* [Information Quality](https://www.defense.gov/Resources/DOD-Information-Quality-Guidelines/)\n* [Open Government](https://data.gov/open-gov/)\n* [Privacy and Civil Liberties](https://dpcld.defense.gov/)\n* [USA.gov](https://www.usa.gov/)"
      ]
    },
    {
      "url": "https://www.crunchbase.com/organization/q-ctrl",
      "title": "Q-CTRL - Crunchbase Company Profile & Funding",
      "publish_date": null,
      "excerpts": [
        "Artificial Intelligence (AI) GPS Information Services Information Technology Navigation Quantum Computing Software Software Engineering ## Funding Rounds\n\nSeries B obfuscated\n\nOBF in obfuscated\n\nobfuscation\n\nGrant obfuscated\n\nOBF in obfuscated\n\nobfuscation\n\nSeries B obfuscated\n\nOBF in obfuscated\n\nobfuscation\n\nView all 10 rounds ## Key People\n\n* Michael Biercuk: Founder and CEO\n  \n  Past Role: Defense Advanced Research Projects Agency, Technical Consultant\n* Robert Love: Chief Technology Officer ## Details\n\nLegal Name Q-CTRL PTY LTD Operating Status Active Company Type For Profit Founders Michael Biercuk\n\nAbout the Company\n\nQ-CTRL is a global pioneer with unmatched commercial traction in the emerging quantum technology industry - a sector poised to transform everything from finance and pharma through to logistics and defense.\nQ-CTRL is a category defining business leading the development of AI-powered quantum infrastructure software, delivering globally unique technology to accelerate the pathway to the world's first useful quantum computers. This same foundational technology also underpins Q-CTRL\u2019s development of novel \u201csoftware-defined\u201d quantum sensors for defense and intelligence. Q-CTRL has assembled the world\u2019s foremost team of expert quantum-control engineers, providing solutions to global quantum technology leaders including Universities, National Labs, and quantum technology industry partners. In May 2023, IBM Quantum announced that Q-CTRL's quantum infrastructure software would be natively embedded in its quantum computing fleet, and the team recently announced a partnership with Transport for NSW - delivering its enterprise infrastructure software to transport data scientists exploring quantum computing."
      ]
    }
  ],
  "warnings": []
}